pyecif/ECIFPandasTools.py
pyecif/__init__.py
pyecif-0.1.2.post2.data/data/README.md
tests/__init__.py
tests/test_ECIFPandasTools.py
pyecif-0.1.2.post2.dist-info/LICENSE
pyecif-0.1.2.post2.dist-info/METADATA
pyecif-0.1.2.post2.dist-info/WHEEL
pyecif-0.1.2.post2.dist-info/top_level.txt
pyecif-0.1.2.post2.dist-info/RECORD
