Metadata-Version: 2.1
Name: pyecif
Version: 0.1.2.post2
Summary: ECIF file format tools for Python.
Home-page: https://github.com/emotionor/ecif
Author: Cui Yaning
Author-email: emotionor@gmail.com
License: MIT
Platform: UNKNOWN
Classifier: License :: OSI Approved :: MIT License
Classifier: Programming Language :: Python :: 3
Classifier: Programming Language :: Python :: 3.8
License-File: LICENSE
Requires-Dist: numpy (>=1.18.5)
Requires-Dist: pandas (>=2.0.0)
Requires-Dist: pymatgen (>=2023.8.10)
Requires-Dist: gemmi
